Metadata-Version: 2.1
Name: poetry-demo-1
Version: 0.1.0
Summary: 
Author: cmejia
Author-email: cmejia@kiusys.com
Requires-Python: >=2.7,<3.0
Classifier: Programming Language :: Python :: 2
Classifier: Programming Language :: Python :: 2.7
Requires-Dist: pendulum (>=2.0.5,<3.0.0)
